{
  "title": "日本の祭り：伝統と情熱の祭典",
  "outline": [
    {
      "level": "H1",
      "text": "祭りの魅力とは？",
      "page": 1
    },
    {
      "level": "H2",
      "text": "四季折々の祭り",
      "page": 1
    },
    {
      "level": "H1",
      "text": "2 ページ目：有名な祭りピックアップ 日本を代表する祭り",
      "page": 1
    },
    {
      "level": "H1",
      "text": "京都祇園祭：千年の歴史を誇る",
      "page": 1
    },
    {
      "level": "H1",
      "text": "青森ねぶた祭：光と音の饗宴",
      "page": 1
    },
    {
      "level": "H2",
      "text": "地域ごとの特色",
      "page": 1
    },
    {
      "level": "H1",
      "text": "3 ページ目：祭りの準備と参加 祭りをもっと楽しむために",
      "page": 1
    },
    {
      "level": "H1",
      "text": "祭りの衣装と小物",
      "page": 1
    },
    {
      "level": "H1",
      "text": "屋台グルメを味わう",
      "page": 2
    },
    {
      "level": "H2",
      "text": "地域との繋がり",
      "page": 2
    },
    {
      "level": "H1",
      "text": "4 ページ目：祭りが伝えるメッセージ 祭りの精神：未来へ繋ぐ",
      "page": 2
    },
    {
      "level": "H1",
      "text": "伝統文化の継承",
      "page": 3
    },
    {
      "level": "H1",
      "text": "人々の願いと祈り",
      "page": 3
    },
    {
      "level": "H2",
      "text": "あなたも祭りに参加してみませんか？",
      "page": 3
    }
  ]
}